CONTRIBUTORS.txt
LICENSE.txt
MANIFEST.in
README.rst
setup.py
django_uni_form.egg-info/PKG-INFO
django_uni_form.egg-info/SOURCES.txt
django_uni_form.egg-info/dependency_links.txt
django_uni_form.egg-info/not-zip-safe
django_uni_form.egg-info/top_level.txt
docs/.DS_Store
docs/Makefile
docs/api_helpers.rst
docs/api_templatetags.rst
docs/changelog.rst
docs/concepts.rst
docs/conf.py
docs/contributors.rst
docs/customization.rst
docs/examples.rst
docs/faq.rst
docs/helpers.rst
docs/index.rst
docs/install.rst
docs/make.bat
docs/usage.rst
docs/_build/.DS_Store
docs/_build/doctrees/api_field.doctree
docs/_build/doctrees/api_filters.doctree
docs/_build/doctrees/api_helpers.doctree
docs/_build/doctrees/api_tags.doctree
docs/_build/doctrees/api_templatetags.doctree
docs/_build/doctrees/changelog.doctree
docs/_build/doctrees/concepts.doctree
docs/_build/doctrees/contributors.doctree
docs/_build/doctrees/customization.doctree
docs/_build/doctrees/docs_todo.doctree
docs/_build/doctrees/environment.pickle
docs/_build/doctrees/examples.doctree
docs/_build/doctrees/faq.doctree
docs/_build/doctrees/helpers.doctree
docs/_build/doctrees/index.doctree
docs/_build/doctrees/install.doctree
docs/_build/doctrees/reference.doctree
docs/_build/doctrees/uni_form_tags.doctree
docs/_build/doctrees/usage.doctree
docs/_build/doctrees/usage_filters.doctree
docs/_build/doctrees/usage_tags.doctree
docs/_build/html/.buildinfo
docs/_build/html/api_field.html
docs/_build/html/api_filters.html
docs/_build/html/api_helpers.html
docs/_build/html/api_tags.html
docs/_build/html/api_templatetags.html
docs/_build/html/changelog.html
docs/_build/html/concepts.html
docs/_build/html/contributors.html
docs/_build/html/customization.html
docs/_build/html/docs_todo.html
docs/_build/html/examples.html
docs/_build/html/faq.html
docs/_build/html/genindex.html
docs/_build/html/helpers.html
docs/_build/html/index.html
docs/_build/html/install.html
docs/_build/html/objects.inv
docs/_build/html/py-modindex.html
docs/_build/html/reference.html
docs/_build/html/search.html
docs/_build/html/searchindex.js
docs/_build/html/uni_form_tags.html
docs/_build/html/usage.html
docs/_build/html/usage_filters.html
