Metadata-Version: 1.0
Name: django-uni-form
Version: 0.8.0
Summary: django-uni-form
Home-page: http://github.com/pydanny/django-uni-form
Author: Daniel Greenfeld
Author-email: pydanny@gmail.com
License: MIT
Keywords: forms,django
Platform: UNKNOWN
Classifier: Development Status :: 5 - Production/Stable
Classifier: Environment :: Web Environment
Classifier: Framework :: Django
Classifier: License :: OSI Approved :: BSD License
Classifier: Operating System :: OS Independent
Classifier: Programming Language :: JavaScript
Classifier: Programming Language :: Python :: 2.6
Classifier: Programming Language :: Python :: 2.7
Classifier: Topic :: Internet :: WWW/HTTP
Classifier: Topic :: Internet :: WWW/HTTP :: Dynamic Content
Classifier: Topic :: Software Development :: Libraries :: Python Modules
